LICENSE
MANIFEST.in
README.md
setup.py
django_vitals.egg-info/PKG-INFO
django_vitals.egg-info/SOURCES.txt
django_vitals.egg-info/dependency_links.txt
django_vitals.egg-info/requires.txt
django_vitals.egg-info/top_level.txt
tests/__init__.py
tests/test_settings.py
tests/tests.py
vitals/__init__.py
vitals/apps.py
vitals/checks.py
vitals/conf.py
vitals/urls.py
vitals/views.py