Metadata-Version: 1.1
Name: django-vitals
Version: 1.0.0
Summary: A django app that provides health check endpoints for vital services.
Home-page: https://github.com/LCOGT/django-vitals
Author: Austin Riba
Author-email: ariba@lcogt.net
License: GPLv2
Platform: UNKNOWN
Classifier: Environment :: Web Environment
Classifier: Framework :: Django
Classifier: Intended Audience :: Developers
Classifier: Programming Language :: Python
Classifier: Programming Language :: Python :: 3
Classifier: Programming Language :: Python :: 3.4
Classifier: Programming Language :: Python :: 3.5
Classifier: Programming Language :: Python :: 3.6
Classifier: Topic :: Internet :: WWW/HTTP
